AutoRegressor/AutomaticRegressio.py
AutoRegressor/__init__.py
MLAutoRegressor-0.0.5.dist-info/LICENSE
MLAutoRegressor-0.0.5.dist-info/METADATA
MLAutoRegressor-0.0.5.dist-info/WHEEL
MLAutoRegressor-0.0.5.dist-info/top_level.txt
MLAutoRegressor-0.0.5.dist-info/RECORD
