Metadata-Version: 2.1
Name: MLAutoRegressor
Version: 0.0.5
Summary: its an implimentation of automatic regression
Home-page: https://github.com/Rohanbagulwar/MLAutoRegressor
Author: Rohan Bagulwar
Author-email: rohanbagulwarrb@gmail.com
License: UNKNOWN
Project-URL: Bug Tracker, https://github.com/Rohanbagulwar/MLAutoRegressor/issues
Platform: UNKNOWN
Classifier: Programming Language :: Python :: 3
Classifier: License :: OSI Approved :: MIT License
Classifier: Operating System :: OS Independent
Requires-Python: >=3.7
License-File: LICENSE
Requires-Dist: numpy
Requires-Dist: pandas
Requires-Dist: joblib
Requires-Dist: scikit-learn
